fints2ledger/__init__.py
fints2ledger/autocomplete.py
fints2ledger/config.py
fints2ledger/csv2ledger.py
fints2ledger/csv_converter.py
fints2ledger/fints2csv.py
fints2ledger/ledger_converter.py
fints2ledger/main.py
fints2ledger/transaction_retriever.py
fints2ledger/utils.py
fints2ledger-0.8.2.dist-info/LICENSE
fints2ledger-0.8.2.dist-info/METADATA
fints2ledger-0.8.2.dist-info/WHEEL
fints2ledger-0.8.2.dist-info/entry_points.txt
fints2ledger-0.8.2.dist-info/top_level.txt
fints2ledger-0.8.2.dist-info/RECORD
