Metadata-Version: 2.1
Name: fints2ledger
Version: 0.8.2
Summary: A tool for downloading transactions from FinTS banking APIs and sorting them into a ledger journal.
Home-page: https://github.com/MoritzR/fints2ledger
Author: Moritz Rumpf
Author-email: moritz.rumpf@gmail.com
License: MIT
Platform: UNKNOWN
Classifier: Development Status :: 3 - Alpha
Classifier: Programming Language :: Python :: 3.7
Classifier: Programming Language :: Python :: 3.8
Classifier: Programming Language :: Python :: 3.9
Classifier: Programming Language :: Python :: 3.10
Classifier: Programming Language :: Python :: 3.11
Requires-Python: >=3.7.0
Requires-Dist: fints (<5,>=4)
Requires-Dist: mt-940 (<5,>=4.11)
Requires-Dist: pyyaml (>=6)
